counter.sv
module counter (
    input  logic clk,        // the clock - the heartbeat
    input  logic rst_n,      // reset (active-low: 0 = reset)
    output logic [3:0] count // 4-bit output: counts 0 to 15
);

    always_ff @(posedge clk) begin
        if (!rst_n)
            count <= 4'd0;       // on reset, go to 0
        else
            count <= count + 1;  // otherwise, add 1 each clock tick
    end

endmodule

tb_counter.sv
module tb_counter;

    logic clk;
    logic rst_n;
    logic [3:0] count;

    // Connect our counter (the "device under test")
    counter dut (
        .clk   (clk),
        .rst_n (rst_n),
        .count (count)
    );

    // Clock generator: flip clk every 5 time units -> a full tick every 10
    always #5 clk = ~clk;

    // The test sequence
    initial begin
        $dumpfile("counter.vcd");   // waveform output file
        $dumpvars(0, tb_counter);   // record all signals

        clk   = 0;
        rst_n = 0;                  // start in reset
        #12;                        // hold reset a moment
        rst_n = 1;                  // release reset - counting begins

        #200;                       // let it run for a while
        $finish;                    // end the simulation
    end

endmodule

counter.vcd
$date
	Tue Jul  7 22:58:11 2026
$end
$version
	Icarus Verilog
$end
$timescale
	1s
$end
$scope module tb_counter $end
$var wire 4 ! count [3:0] $end
$var reg 1 " clk $end
$var reg 1 # rst_n $end
$scope module dut $end
$var wire 1 " clk $end
$var wire 1 # rst_n $end
$var reg 4 $ count [3:0] $end
$upscope $end
$upscope $end
$enddefinitions $end
$comment Show the parameter values. $end
$dumpall
$end
#0
$dumpvars
bx $
0#
0"
bx !
$end
#5
b0 !
b0 $
1"
#10
0"
1#
#15
b1 !
b1 $
1"
#20
0"
#25
b10 !
b10 $
1"
#30
0"
#35
b11 !
b11 $
1"
#40
0"
#45
b100 !
b100 $
1"
#50
0"
#55
b101 !
b101 $
1"
#60
0"
#65
b110 !
b110 $
1"
#70
0"
#75
b111 !
b111 $
1"
#80
0"
#85
b1000 !
b1000 $
1"
#90
0"
#95
b1001 !
b1001 $
1"
#100
0"
#105
b1010 !
b1010 $
1"
#110
0"
#115
b1011 !
b1011 $
1"
#120
0"
#125
b1100 !
b1100 $
1"
#130
0"
#135
b1101 !
b1101 $
1"
#140
0"
#145
b1110 !
b1110 $
1"
#150
0"
#155
b1111 !
b1111 $
1"
#160
0"
#165
b0 !
b0 $
1"
#170
0"
#175
b1 !
b1 $
1"
#180
0"
#185
b10 !
b10 $
1"
#190
0"
#195
b11 !
b11 $
1"
#200
0"
#205
b100 !
b100 $
1"
