rtl/register.sv
module register (
    input  logic       clk,
    input  logic       rst_n,
    input  logic       en,
    input  logic [7:0] data_in,
    output logic [7:0] data_out
);

always_ff @(posedge clk) begin
    if (!rst_n)
        data_out <= 8'h00;
    else if (en)
        data_out <= data_in;
end

endmodule

tb/tb_register.sv
module tb_register;

    logic clk;
    logic rst_n;
    logic en;
    logic [7:0] data_in;
    logic [7:0] data_out;
    register dut (
        .clk(clk),
        .rst_n(rst_n),
        .en(en),
        .data_in(data_in),
        .data_out(data_out)
    );

    always #5 clk = ~clk;

    initial begin
        $dumpfile("register.vcd");
        $dumpvars(0, tb_register);

        clk = 0;
        rst_n = 0;
        en = 0;
        data_in = 8'h00;

        #10;
        rst_n = 1;

        #10;
        en = 1;
        data_in = 8'h41;

        #10;
        data_in = 8'h55;

        #10;
        en = 0;
        data_in = 8'hAA;

        #20;
        $finish;
    end

endmodule

register.vcd
$date
	Tue Jul  7 22:42:38 2026
$end
$version
	Icarus Verilog
$end
$timescale
	1s
$end
$scope module tb_register $end
$var wire 8 ! data_out [7:0] $end
$var reg 1 " clk $end
$var reg 8 # data_in [7:0] $end
$var reg 1 $ en $end
$var reg 1 % rst_n $end
$scope module dut $end
$var wire 1 " clk $end
$var wire 8 & data_in [7:0] $end
$var wire 1 $ en $end
$var wire 1 % rst_n $end
$var reg 8 ' data_out [7:0] $end
$upscope $end
$upscope $end
$enddefinitions $end
$comment Show the parameter values. $end
$dumpall
$end
#0
$dumpvars
bx '
b0 &
0%
0$
b0 #
0"
bx !
$end
#5
b0 !
b0 '
1"
#10
0"
1%
#15
1"
#20
0"
b1000001 #
b1000001 &
1$
#25
b1000001 !
b1000001 '
1"
#30
0"
b1010101 #
b1010101 &
#35
b1010101 !
b1010101 '
1"
#40
0"
b10101010 #
b10101010 &
0$
